combine_tex/__init__.py
combine_tex/command_line.py
combine_tex-0.1.0.dist-info/DESCRIPTION.rst
combine_tex-0.1.0.dist-info/METADATA
combine_tex-0.1.0.dist-info/RECORD
combine_tex-0.1.0.dist-info/WHEEL
combine_tex-0.1.0.dist-info/entry_points.txt
combine_tex-0.1.0.dist-info/metadata.json
combine_tex-0.1.0.dist-info/top_level.txt
