Metadata-Version: 2.0
Name: combine-tex
Version: 0.1.0
Summary: Command line python script to combine multiple .tex files into one
Home-page: https://github.com/dannyzed/combine-tex
Author: Daniel Zawada
Author-email: zawadadaniel@gmail.com
License: MIT
Platform: UNKNOWN
